astm/__init__.py
astm/asynclib.py
astm/client.py
astm/codec.py
astm/constants.py
astm/exceptions.py
astm/mapping.py
astm/protocol.py
astm/records.py
astm/server.py
astm/version.py
astm/omnilab/__init__.py
astm/omnilab/client.py
astm/omnilab/common.py
astm/omnilab/server.py
astm/tests/__init__.py
astm/tests/test_asynclib.py
astm/tests/test_client.py
astm/tests/test_codecs.py
astm/tests/test_mapping.py
astm/tests/test_omnilab.py
astm/tests/test_protocol.py
astm/tests/test_server.py
astm/tests/utils.py
astm_2025-1.0.0.dist-info/licenses/COPYING
astm_2025-1.0.0.dist-info/METADATA
astm_2025-1.0.0.dist-info/WHEEL
astm_2025-1.0.0.dist-info/top_level.txt
astm_2025-1.0.0.dist-info/zip-safe
astm_2025-1.0.0.dist-info/RECORD
